amply/__init__.py
amply/client.py
amply/email.py
amply/exceptions.py
amply/version.py
amply/helpers/__init__.py
amply/helpers/email/__init__.py
amply/helpers/email/email_address.py
amply_mail-0.0.1rc2.dist-info/LICENSE
amply_mail-0.0.1rc2.dist-info/METADATA
amply_mail-0.0.1rc2.dist-info/WHEEL
amply_mail-0.0.1rc2.dist-info/top_level.txt
amply_mail-0.0.1rc2.dist-info/RECORD
