Metadata-Version: 2.1
Name: amply-mail
Version: 0.0.1rc2
Summary: This is the Amply Python SDK that integrates with the v1 API.
Home-page: https://github.com/sendamply/amply-python
License: MIT
Keywords: amply,email
Platform: UNKNOWN
Requires-Dist: requests
